geostats/Kriging.py
geostats/__init__.py
geostats/build_Mrho/build_Mrho.c
geostats/build_Mrho/build_Mrho.cp39-win_amd64.pyd
geostats/build_Mrho/build_Mrho.cpython-39-x86_64-linux-gnu.so
geostats/build_Mrho/build_Mrho.pyx
geostats/geostats_tools/geostats_tools.c
geostats/geostats_tools/geostats_tools.cp39-win_amd64.pyd
geostats/geostats_tools/geostats_tools.cpython-39-x86_64-linux-gnu.so
geostats/geostats_tools/geostats_tools.pyx
geostats-0.1.0.dist-info/LICENSE
geostats-0.1.0.dist-info/METADATA
geostats-0.1.0.dist-info/WHEEL
geostats-0.1.0.dist-info/top_level.txt
geostats-0.1.0.dist-info/RECORD
