Metadata-Version: 2.1
Name: geostats
Version: 0.1.0
Summary: A suite of geostatistical tools.
Home-page: https://github.com/RPretellD/geostats
Author: A. Renmin Pretell Ductram
Author-email: rpretell@unr.edu
License: MIT
Keywords: geostats
Classifier: Programming Language :: Python :: 3
Classifier: License :: OSI Approved :: MIT License
Requires-Python: >=3.6
License-File: LICENSE
Requires-Dist: numpy
Requires-Dist: Cython
